{
	"display": {
		"icon": {
			"item": "minecraft:emerald_block"
		},
		"title": {
			"text": "Serious Renovations",
			"color": "white"
		},
		"description": [
			{
				"text": "Place ",
				"color": "white"
			},
			{
				"text": "10k",
				"color": "#5991ec"
			},
			{
				"text": " blocks in ",
				"color": "white"
			},
			{
				"text": "Pocket Dimension",
				"color": "#acff94"
			}
		],
		"frame": "challenge"
	},
	"parent": "pocket_dimension:building/a_new_home",
	"criteria": {
		"build_1k_in_pocket_dimension": {
			"trigger": "minecraft:impossible"
		}
	}
}