{
	"display": {
		"icon": {
			"item": "minecraft:filled_map"
		},
		"title": {
			"text": "In Case I Built a Maze",
			"color": "white"
		},
		"description": [
			{	
				"text": "Create a ",
				"color": "white"
			},
			{	
				"text": "map",
				"color": "#ffd12f"
			},
			{	
				"text": " of ",
				"color": "white"
			},
			{
				"text": "Pocket Dimension",
				"color": "#5991ec"
			}
		],
		"frame": "goal"
	},
	"parent": "pocket_dimension:make_yourself_at_home/root",
	"criteria": {
		"granted_manually": {
			"trigger": "impossible"
		}
	},
	"rewards": {
		"function": "pocket_dimension:advancements/make_yourself_at_home/in_case_i_built_a_maze"
	}
}